Gpxity-1.7.2.data/scripts/gpxdo
Gpxity-1.7.2.data/scripts/gpxity_server
gpxity/__init__.py
gpxity/accounts.py
gpxity/backend.py
gpxity/backend_base.py
gpxity/diff.py
gpxity/gpx.py
gpxity/gpxfile.py
gpxity/lifetrack.py
gpxity/locate.py
gpxity/util.py
gpxity/version.py
gpxity/backends/__init__.py
gpxity/backends/directory.py
gpxity/backends/gpsies.py
gpxity/backends/mailer.py
gpxity/backends/memory.py
gpxity/backends/mmt.py
gpxity/backends/openrunner.py
gpxity/backends/trackmmt.py
gpxity/backends/wptrackserver.py
gpxity/backends/test/__init__.py
gpxity/backends/test/basic.py
gpxity/backends/test/test.gpx
gpxity/backends/test/test2.gpx
gpxity/backends/test/test_backends.py
gpxity/backends/test/test_track.py
gpxity/test/__init__.py
gpxity/test/test_gpx.py
Gpxity-1.7.2.dist-info/LICENSE
Gpxity-1.7.2.dist-info/METADATA
Gpxity-1.7.2.dist-info/WHEEL
Gpxity-1.7.2.dist-info/top_level.txt
Gpxity-1.7.2.dist-info/RECORD
