Metadata-Version: 2.1
Name: Gpxity
Version: 1.7.2
Summary: A uniform interface to GPX services like mapmytracks or gpsies
Home-page: https://github.com/wrohdewald/Gpxity
Author: Wolfgang Rohdewald
Author-email: wolfgang@rohdewald.de
License: GPLv2
Platform: UNKNOWN
Classifier: Development Status :: 4 - Beta
Classifier: Environment :: Web Environment
Classifier: Intended Audience :: Developers
Classifier: License :: OSI Approved :: GNU General Public License v2 (GPLv2)
Classifier: Operating System :: OS Independent
Classifier: Programming Language :: Python :: 3.5
Classifier: Programming Language :: Python :: 3.6
Classifier: Programming Language :: Python :: 3 :: Only
Classifier: Topic :: Communications
Classifier: Topic :: Internet :: WWW/HTTP
Requires-Dist: geocoder (>=1.38)
Requires-Dist: gpxpy (>=1.2.0)
Requires-Dist: lxml
Requires-Dist: requests
Provides-Extra: wptrackserver
Requires-Dist: mysqlclient ; extra == 'wptrackserver'
Provides-Extra: develop
Requires-Dist: aiosmtpd ; extra == 'develop'
Requires-Dist: coverage ; extra == 'develop'
Requires-Dist: pytest ; extra == 'develop'
Provides-Extra: doc
Requires-Dist: sphinx ; extra == 'doc'
Requires-Dist: sphinx-argparse ; extra == 'doc'
Requires-Dist: sphinx-autodoc-annotation ; extra == 'doc'
